{
  "$schema": "exam-tutor/question-bank/v1",
  "metadata": {
    "exam_type": "KPPSC",
    "subject": "Pakistan Studies",
    "topic": "Comprehensive",
    "source": "compiled",
    "created_at": "2026-01-27T00:00:00Z",
    "question_count": 100
  },
  "questions": [
    {"id": "KPPSC-PK-00101", "text": "Khyber Pakhtunkhwa was known as NWFP until:", "options": {"A": "2008", "B": "2010", "C": "2012", "D": "2014"}, "correct_answer": "B", "topic": "History", "difficulty": "easy"},
    {"id": "KPPSC-PK-00102", "text": "The capital of Khyber Pakhtunkhwa is:", "options": {"A": "Abbottabad", "B": "Peshawar", "C": "Mardan", "D": "Swat"}, "correct_answer": "B", "topic": "Geography", "difficulty": "easy"},
    {"id": "KPPSC-PK-00103", "text": "The largest city of KPK by population is:", "options": {"A": "Mardan", "B": "Peshawar", "C": "Abbottabad", "D": "Swat"}, "correct_answer": "B", "topic": "Geography", "difficulty": "easy"},
    {"id": "KPPSC-PK-00104", "text": "Khyber Pass connects Pakistan with:", "options": {"A": "Iran", "B": "Afghanistan", "C": "China", "D": "India"}, "correct_answer": "B", "topic": "Geography", "difficulty": "easy"},
    {"id": "KPPSC-PK-00105", "text": "Torkham is located on the border of:", "options": {"A": "Pakistan-Iran", "B": "Pakistan-Afghanistan", "C": "Pakistan-China", "D": "Pakistan-India"}, "correct_answer": "B", "topic": "Geography", "difficulty": "easy"},
    {"id": "KPPSC-PK-00106", "text": "The highest mountain of KPK is:", "options": {"A": "Nanga Parbat", "B": "Tirich Mir", "C": "K2", "D": "Rakaposhi"}, "correct_answer": "B", "topic": "Geography", "difficulty": "easy"},
    {"id": "KPPSC-PK-00107", "text": "Tirich Mir is located in:", "options": {"A": "Karakoram", "B": "Hindu Kush", "C": "Himalayas", "D": "Sulaiman"}, "correct_answer": "B", "topic": "Geography", "difficulty": "easy"},
    {"id": "KPPSC-PK-00108", "text": "Swat Valley is known as:", "options": {"A": "City of Saints", "B": "Switzerland of Pakistan", "C": "Fruit Basket", "D": "City of Gardens"}, "correct_answer": "B", "topic": "Geography", "difficulty": "easy"},
    {"id": "KPPSC-PK-00109", "text": "Takht-i-Bahi is an ancient Buddhist site in:", "options": {"A": "Peshawar", "B": "Mardan", "C": "Swabi", "D": "Charsadda"}, "correct_answer": "B", "topic": "History", "difficulty": "easy"},
    {"id": "KPPSC-PK-00110", "text": "The archaeological site of Gandhara is mainly in:", "options": {"A": "Punjab", "B": "KPK", "C": "Sindh", "D": "Balochistan"}, "correct_answer": "B", "topic": "History", "difficulty": "easy"},
    {"id": "KPPSC-PK-00111", "text": "Khan Abdul Ghaffar Khan was known as:", "options": {"A": "Quaid-e-Azam", "B": "Bacha Khan", "C": "Khan Sahib", "D": "Frontier Gandhi"}, "correct_answer": "B", "topic": "History", "difficulty": "easy"},
    {"id": "KPPSC-PK-00112", "text": "Bacha Khan founded the:", "options": {"A": "Muslim League", "B": "Khudai Khidmatgar", "C": "Congress", "D": "Jamiat Ulema-e-Hind"}, "correct_answer": "B", "topic": "History", "difficulty": "easy"},
    {"id": "KPPSC-PK-00113", "text": "Khudai Khidmatgar movement was started in:", "options": {"A": "1927", "B": "1929", "C": "1931", "D": "1933"}, "correct_answer": "B", "topic": "History", "difficulty": "medium"},
    {"id": "KPPSC-PK-00114", "text": "The Red Shirts were members of:", "options": {"A": "Muslim League", "B": "Khudai Khidmatgar", "C": "Congress", "D": "Jamiat Ulema-e-Hind"}, "correct_answer": "B", "topic": "History", "difficulty": "easy"},
    {"id": "KPPSC-PK-00115", "text": "NWFP was created as a separate province in:", "options": {"A": "1899", "B": "1901", "C": "1903", "D": "1905"}, "correct_answer": "B", "topic": "History", "difficulty": "medium"},
    {"id": "KPPSC-PK-00116", "text": "NWFP was created by:", "options": {"A": "Lord Minto", "B": "Lord Curzon", "C": "Lord Ripon", "D": "Lord Lytton"}, "correct_answer": "B", "topic": "History", "difficulty": "medium"},
    {"id": "KPPSC-PK-00117", "text": "The referendum for joining Pakistan was held in NWFP in:", "options": {"A": "June 1947", "B": "July 1947", "C": "August 1947", "D": "September 1947"}, "correct_answer": "B", "topic": "History", "difficulty": "medium"},
    {"id": "KPPSC-PK-00118", "text": "In the 1947 referendum, NWFP voted for:", "options": {"A": "India", "B": "Pakistan", "C": "Independence", "D": "Afghanistan"}, "correct_answer": "B", "topic": "History", "difficulty": "easy"},
    {"id": "KPPSC-PK-00119", "text": "Peshawar was the capital of which ancient empire?", "options": {"A": "Mauryan", "B": "Kushan", "C": "Mughal", "D": "British"}, "correct_answer": "B", "topic": "History", "difficulty": "medium"},
    {"id": "KPPSC-PK-00120", "text": "King Kanishka belonged to:", "options": {"A": "Mauryan Dynasty", "B": "Kushan Dynasty", "C": "Mughal Dynasty", "D": "Gupta Dynasty"}, "correct_answer": "B", "topic": "History", "difficulty": "medium"},
    {"id": "KPPSC-PK-00121", "text": "Pakistan joined UN on:", "options": {"A": "August 1947", "B": "September 1947", "C": "October 1947", "D": "November 1947"}, "correct_answer": "B", "topic": "Foreign Relations", "difficulty": "medium"},
    {"id": "KPPSC-PK-00122", "text": "Pakistan's seat in UN General Assembly is:", "options": {"A": "Permanent", "B": "Rotating", "C": "Observer", "D": "Honorary"}, "correct_answer": "B", "topic": "Foreign Relations", "difficulty": "easy"},
    {"id": "KPPSC-PK-00123", "text": "Pakistan has been elected to UN Security Council:", "options": {"A": "5 times", "B": "7 times", "C": "9 times", "D": "11 times"}, "correct_answer": "B", "topic": "Foreign Relations", "difficulty": "hard"},
    {"id": "KPPSC-PK-00124", "text": "SAARC was founded in:", "options": {"A": "1983", "B": "1985", "C": "1987", "D": "1989"}, "correct_answer": "B", "topic": "Foreign Relations", "difficulty": "easy"},
    {"id": "KPPSC-PK-00125", "text": "SAARC headquarters is in:", "options": {"A": "Islamabad", "B": "Kathmandu", "C": "Dhaka", "D": "New Delhi"}, "correct_answer": "B", "topic": "Foreign Relations", "difficulty": "easy"},
    {"id": "KPPSC-PK-00126", "text": "How many countries are members of SAARC?", "options": {"A": "6", "B": "8", "C": "10", "D": "12"}, "correct_answer": "B", "topic": "Foreign Relations", "difficulty": "easy"},
    {"id": "KPPSC-PK-00127", "text": "ECO (Economic Cooperation Organization) has:", "options": {"A": "8 members", "B": "10 members", "C": "12 members", "D": "14 members"}, "correct_answer": "B", "topic": "Foreign Relations", "difficulty": "hard"},
    {"id": "KPPSC-PK-00128", "text": "ECO headquarters is in:", "options": {"A": "Islamabad", "B": "Tehran", "C": "Ankara", "D": "Baku"}, "correct_answer": "B", "topic": "Foreign Relations", "difficulty": "medium"},
    {"id": "KPPSC-PK-00129", "text": "D-8 organization was founded in:", "options": {"A": "1995", "B": "1997", "C": "1999", "D": "2001"}, "correct_answer": "B", "topic": "Foreign Relations", "difficulty": "medium"},
    {"id": "KPPSC-PK-00130", "text": "Shanghai Cooperation Organization was founded in:", "options": {"A": "1999", "B": "2001", "C": "2003", "D": "2005"}, "correct_answer": "B", "topic": "Foreign Relations", "difficulty": "medium"},
    {"id": "KPPSC-PK-00131", "text": "Pakistan became member of SCO in:", "options": {"A": "2015", "B": "2017", "C": "2019", "D": "2021"}, "correct_answer": "B", "topic": "Foreign Relations", "difficulty": "medium"},
    {"id": "KPPSC-PK-00132", "text": "The first Chief Election Commissioner of Pakistan was:", "options": {"A": "Justice Cornelius", "B": "Justice Rahim", "C": "Justice Kayani", "D": "Justice Chaudhry"}, "correct_answer": "A", "topic": "History", "difficulty": "hard"},
    {"id": "KPPSC-PK-00133", "text": "Election Commission of Pakistan was established in:", "options": {"A": "1954", "B": "1956", "C": "1958", "D": "1960"}, "correct_answer": "B", "topic": "Constitutional History", "difficulty": "hard"},
    {"id": "KPPSC-PK-00134", "text": "NADRA was established in:", "options": {"A": "1998", "B": "2000", "C": "2002", "D": "2004"}, "correct_answer": "B", "topic": "Administration", "difficulty": "medium"},
    {"id": "KPPSC-PK-00135", "text": "NADRA stands for:", "options": {"A": "National Authority for Data and Registration Authority", "B": "National Database and Registration Authority", "C": "National Data Base for Registration Authority", "D": "None of these"}, "correct_answer": "B", "topic": "Administration", "difficulty": "easy"},
    {"id": "KPPSC-PK-00136", "text": "FBR was previously known as:", "options": {"A": "Income Tax Department", "B": "CBR", "C": "Revenue Board", "D": "Tax Authority"}, "correct_answer": "B", "topic": "Administration", "difficulty": "easy"},
    {"id": "KPPSC-PK-00137", "text": "FBR stands for:", "options": {"A": "Federal Board of Revenue", "B": "Finance Board of Revenue", "C": "Federal Bureau of Revenue", "D": "Finance Bureau of Revenue"}, "correct_answer": "A", "topic": "Administration", "difficulty": "easy"},
    {"id": "KPPSC-PK-00138", "text": "NAB was established in:", "options": {"A": "1997", "B": "1999", "C": "2001", "D": "2003"}, "correct_answer": "B", "topic": "Administration", "difficulty": "medium"},
    {"id": "KPPSC-PK-00139", "text": "NAB stands for:", "options": {"A": "National Accountability Board", "B": "National Accountability Bureau", "C": "National Anti-corruption Bureau", "D": "None of these"}, "correct_answer": "B", "topic": "Administration", "difficulty": "easy"},
    {"id": "KPPSC-PK-00140", "text": "The Supreme Court of Pakistan is located in:", "options": {"A": "Lahore", "B": "Islamabad", "C": "Karachi", "D": "Peshawar"}, "correct_answer": "B", "topic": "Judiciary", "difficulty": "easy"},
    {"id": "KPPSC-PK-00141", "text": "High Courts in Pakistan are:", "options": {"A": "4", "B": "5", "C": "6", "D": "7"}, "correct_answer": "B", "topic": "Judiciary", "difficulty": "medium"},
    {"id": "KPPSC-PK-00142", "text": "Peshawar High Court was established in:", "options": {"A": "1944", "B": "1946", "C": "1948", "D": "1950"}, "correct_answer": "B", "topic": "Judiciary", "difficulty": "hard"},
    {"id": "KPPSC-PK-00143", "text": "Federal Shariat Court was established in:", "options": {"A": "1978", "B": "1980", "C": "1982", "D": "1984"}, "correct_answer": "B", "topic": "Judiciary", "difficulty": "medium"},
    {"id": "KPPSC-PK-00144", "text": "The tenure of Chief Justice of Pakistan is:", "options": {"A": "3 years", "B": "Until age 65", "C": "5 years", "D": "7 years"}, "correct_answer": "B", "topic": "Judiciary", "difficulty": "medium"},
    {"id": "KPPSC-PK-00145", "text": "The tenure of High Court Judge is:", "options": {"A": "Until age 60", "B": "Until age 62", "C": "Until age 65", "D": "5 years"}, "correct_answer": "B", "topic": "Judiciary", "difficulty": "medium"},
    {"id": "KPPSC-PK-00146", "text": "Pakistan Army was established on:", "options": {"A": "August 14, 1947", "B": "August 15, 1947", "C": "April 1, 1947", "D": "January 1, 1948"}, "correct_answer": "A", "topic": "Defense", "difficulty": "medium"},
    {"id": "KPPSC-PK-00147", "text": "Pakistan Air Force Day is celebrated on:", "options": {"A": "September 6", "B": "September 7", "C": "April 14", "D": "March 23"}, "correct_answer": "B", "topic": "Defense", "difficulty": "medium"},
    {"id": "KPPSC-PK-00148", "text": "Pakistan Navy Day is celebrated on:", "options": {"A": "September 6", "B": "September 8", "C": "September 7", "D": "October 21"}, "correct_answer": "B", "topic": "Defense", "difficulty": "medium"},
    {"id": "KPPSC-PK-00149", "text": "GHQ of Pakistan Army is in:", "options": {"A": "Islamabad", "B": "Rawalpindi", "C": "Lahore", "D": "Karachi"}, "correct_answer": "B", "topic": "Defense", "difficulty": "easy"},
    {"id": "KPPSC-PK-00150", "text": "Pakistan Military Academy is located in:", "options": {"A": "Rawalpindi", "B": "Kakul", "C": "Quetta", "D": "Risalpur"}, "correct_answer": "B", "topic": "Defense", "difficulty": "easy"},
    {"id": "KPPSC-PK-00151", "text": "PAF Academy is located at:", "options": {"A": "Karachi", "B": "Risalpur", "C": "Multan", "D": "Peshawar"}, "correct_answer": "B", "topic": "Defense", "difficulty": "easy"},
    {"id": "KPPSC-PK-00152", "text": "Pakistan Naval Academy is located at:", "options": {"A": "Karachi", "B": "Manora", "C": "Gwadar", "D": "Ormara"}, "correct_answer": "B", "topic": "Defense", "difficulty": "medium"},
    {"id": "KPPSC-PK-00153", "text": "Command and Staff College is located at:", "options": {"A": "Rawalpindi", "B": "Quetta", "C": "Lahore", "D": "Karachi"}, "correct_answer": "B", "topic": "Defense", "difficulty": "easy"},
    {"id": "KPPSC-PK-00154", "text": "National Defence University is located in:", "options": {"A": "Rawalpindi", "B": "Islamabad", "C": "Quetta", "D": "Lahore"}, "correct_answer": "B", "topic": "Defense", "difficulty": "easy"},
    {"id": "KPPSC-PK-00155", "text": "Pakistan's missile Ghauri has a range of approximately:", "options": {"A": "1000 km", "B": "1500 km", "C": "2000 km", "D": "2500 km"}, "correct_answer": "B", "topic": "Defense", "difficulty": "hard"},
    {"id": "KPPSC-PK-00156", "text": "Pakistan's missile Shaheen-III has a range of:", "options": {"A": "2000 km", "B": "2750 km", "C": "3000 km", "D": "3500 km"}, "correct_answer": "B", "topic": "Defense", "difficulty": "hard"},
    {"id": "KPPSC-PK-00157", "text": "JF-17 Thunder is a joint project with:", "options": {"A": "USA", "B": "China", "C": "Russia", "D": "France"}, "correct_answer": "B", "topic": "Defense", "difficulty": "easy"},
    {"id": "KPPSC-PK-00158", "text": "Pakistan became nuclear power in:", "options": {"A": "1996", "B": "1998", "C": "2000", "D": "2002"}, "correct_answer": "B", "topic": "Defense", "difficulty": "easy"},
    {"id": "KPPSC-PK-00159", "text": "The first Pakistani astronaut is:", "options": {"A": "Namira Salim", "B": "Never been one", "C": "Abdul Sattar", "D": "Rashid Minhas"}, "correct_answer": "B", "topic": "Science", "difficulty": "hard"},
    {"id": "KPPSC-PK-00160", "text": "Pakistan Space and Upper Atmosphere Research Commission (SUPARCO) was established in:", "options": {"A": "1959", "B": "1961", "C": "1963", "D": "1965"}, "correct_answer": "B", "topic": "Science", "difficulty": "hard"},
    {"id": "KPPSC-PK-00161", "text": "Pakistan's first satellite Badr-1 was launched in:", "options": {"A": "1988", "B": "1990", "C": "1992", "D": "1994"}, "correct_answer": "B", "topic": "Science", "difficulty": "medium"},
    {"id": "KPPSC-PK-00162", "text": "PakSat-1R was launched in:", "options": {"A": "2009", "B": "2011", "C": "2013", "D": "2015"}, "correct_answer": "B", "topic": "Science", "difficulty": "hard"},
    {"id": "KPPSC-PK-00163", "text": "Pakistan Atomic Energy Commission (PAEC) was established in:", "options": {"A": "1954", "B": "1956", "C": "1958", "D": "1960"}, "correct_answer": "B", "topic": "Science", "difficulty": "medium"},
    {"id": "KPPSC-PK-00164", "text": "Chashma Nuclear Power Plants are in:", "options": {"A": "Sindh", "B": "Punjab", "C": "KPK", "D": "Balochistan"}, "correct_answer": "B", "topic": "Science", "difficulty": "easy"},
    {"id": "KPPSC-PK-00165", "text": "PINSTECH is located in:", "options": {"A": "Karachi", "B": "Islamabad", "C": "Lahore", "D": "Multan"}, "correct_answer": "B", "topic": "Science", "difficulty": "hard"},
    {"id": "KPPSC-PK-00166", "text": "National Institute of Health is located in:", "options": {"A": "Karachi", "B": "Islamabad", "C": "Lahore", "D": "Peshawar"}, "correct_answer": "B", "topic": "Health", "difficulty": "easy"},
    {"id": "KPPSC-PK-00167", "text": "Shaukat Khanum Memorial Cancer Hospital was founded by:", "options": {"A": "Pervez Musharraf", "B": "Imran Khan", "C": "Nawaz Sharif", "D": "Asif Zardari"}, "correct_answer": "B", "topic": "Health", "difficulty": "easy"},
    {"id": "KPPSC-PK-00168", "text": "First heart transplant in Pakistan was performed in:", "options": {"A": "2005", "B": "2007", "C": "2009", "D": "2011"}, "correct_answer": "B", "topic": "Health", "difficulty": "hard"},
    {"id": "KPPSC-PK-00169", "text": "Pakistan Medical and Dental Council (PMDC) was established in:", "options": {"A": "1960", "B": "1962", "C": "1964", "D": "1966"}, "correct_answer": "B", "topic": "Health", "difficulty": "hard"},
    {"id": "KPPSC-PK-00170", "text": "Aga Khan University Hospital is located in:", "options": {"A": "Lahore", "B": "Karachi", "C": "Islamabad", "D": "Peshawar"}, "correct_answer": "B", "topic": "Health", "difficulty": "easy"},
    {"id": "KPPSC-PK-00171", "text": "The total districts in KPK are:", "options": {"A": "30", "B": "35", "C": "37", "D": "40"}, "correct_answer": "B", "topic": "Geography", "difficulty": "hard"},
    {"id": "KPPSC-PK-00172", "text": "The total divisions in KPK are:", "options": {"A": "5", "B": "7", "C": "9", "D": "11"}, "correct_answer": "B", "topic": "Geography", "difficulty": "hard"},
    {"id": "KPPSC-PK-00173", "text": "Warsak Dam is on river:", "options": {"A": "Indus", "B": "Kabul", "C": "Swat", "D": "Panjkora"}, "correct_answer": "B", "topic": "Geography", "difficulty": "easy"},
    {"id": "KPPSC-PK-00174", "text": "The major river of KPK is:", "options": {"A": "Indus", "B": "Kabul", "C": "Swat", "D": "All of these"}, "correct_answer": "D", "topic": "Geography", "difficulty": "easy"},
    {"id": "KPPSC-PK-00175", "text": "Peshawar means:", "options": {"A": "City of Gardens", "B": "City of Flowers", "C": "City of Men", "D": "City of Saints"}, "correct_answer": "B", "topic": "Geography", "difficulty": "medium"},
    {"id": "KPPSC-PK-00176", "text": "Islamia College Peshawar was established in:", "options": {"A": "1911", "B": "1913", "C": "1915", "D": "1917"}, "correct_answer": "B", "topic": "Education", "difficulty": "hard"},
    {"id": "KPPSC-PK-00177", "text": "University of Peshawar was established in:", "options": {"A": "1948", "B": "1950", "C": "1952", "D": "1954"}, "correct_answer": "B", "topic": "Education", "difficulty": "medium"},
    {"id": "KPPSC-PK-00178", "text": "Ayub National Park is located near:", "options": {"A": "Peshawar", "B": "Rawalpindi", "C": "Lahore", "D": "Karachi"}, "correct_answer": "B", "topic": "Geography", "difficulty": "medium"},
    {"id": "KPPSC-PK-00179", "text": "Chitral borders which country?", "options": {"A": "China", "B": "Afghanistan", "C": "Both A and B", "D": "None"}, "correct_answer": "C", "topic": "Geography", "difficulty": "medium"},
    {"id": "KPPSC-PK-00180", "text": "Kalash Valley is located in:", "options": {"A": "Swat", "B": "Chitral", "C": "Dir", "D": "Kohistan"}, "correct_answer": "B", "topic": "Geography", "difficulty": "easy"},
    {"id": "KPPSC-PK-00181", "text": "The Kalash people are known for their:", "options": {"A": "Islamic traditions", "B": "Unique culture and religion", "C": "Hindu practices", "D": "Buddhist heritage"}, "correct_answer": "B", "topic": "Culture", "difficulty": "easy"},
    {"id": "KPPSC-PK-00182", "text": "Peshawar Museum is famous for:", "options": {"A": "Mughal artifacts", "B": "Gandhara art", "C": "Modern art", "D": "Islamic calligraphy"}, "correct_answer": "B", "topic": "Culture", "difficulty": "easy"},
    {"id": "KPPSC-PK-00183", "text": "Dir became a district in:", "options": {"A": "1968", "B": "1970", "C": "1972", "D": "1974"}, "correct_answer": "B", "topic": "History", "difficulty": "hard"},
    {"id": "KPPSC-PK-00184", "text": "Swat State merged with Pakistan in:", "options": {"A": "1967", "B": "1969", "C": "1971", "D": "1973"}, "correct_answer": "B", "topic": "History", "difficulty": "hard"},
    {"id": "KPPSC-PK-00185", "text": "Last Wali of Swat was:", "options": {"A": "Miangul Jahanzeb", "B": "Miangul Abdul Haq Jehanzeb", "C": "Abdul Wadud", "D": "Shujauddaulah"}, "correct_answer": "B", "topic": "History", "difficulty": "hard"},
    {"id": "KPPSC-PK-00186", "text": "Operation Rah-e-Rast was conducted in:", "options": {"A": "2007", "B": "2009", "C": "2011", "D": "2013"}, "correct_answer": "B", "topic": "History", "difficulty": "medium"},
    {"id": "KPPSC-PK-00187", "text": "Army Public School Peshawar attack occurred in:", "options": {"A": "2012", "B": "2014", "C": "2016", "D": "2018"}, "correct_answer": "B", "topic": "History", "difficulty": "easy"},
    {"id": "KPPSC-PK-00188", "text": "National Action Plan (NAP) was adopted after APS attack in:", "options": {"A": "December 2014", "B": "January 2015", "C": "February 2015", "D": "March 2015"}, "correct_answer": "B", "topic": "History", "difficulty": "medium"},
    {"id": "KPPSC-PK-00189", "text": "Operation Zarb-e-Azb was launched in:", "options": {"A": "2012", "B": "2014", "C": "2016", "D": "2018"}, "correct_answer": "B", "topic": "History", "difficulty": "easy"},
    {"id": "KPPSC-PK-00190", "text": "Operation Zarb-e-Azb was conducted in:", "options": {"A": "Swat", "B": "North Waziristan", "C": "South Waziristan", "D": "Bajaur"}, "correct_answer": "B", "topic": "History", "difficulty": "easy"},
    {"id": "KPPSC-PK-00191", "text": "FATA stands for:", "options": {"A": "Federal Administration Tribal Areas", "B": "Federally Administered Tribal Areas", "C": "Federal Autonomous Tribal Areas", "D": "Federally Autonomous Tribal Areas"}, "correct_answer": "B", "topic": "Geography", "difficulty": "easy"},
    {"id": "KPPSC-PK-00192", "text": "FATA merged with KPK in:", "options": {"A": "2016", "B": "2018", "C": "2020", "D": "2022"}, "correct_answer": "B", "topic": "Constitutional History", "difficulty": "easy"},
    {"id": "KPPSC-PK-00193", "text": "Tribal districts in KPK after FATA merger are:", "options": {"A": "5", "B": "7", "C": "9", "D": "11"}, "correct_answer": "B", "topic": "Geography", "difficulty": "hard"},
    {"id": "KPPSC-PK-00194", "text": "Bajaur Agency was merged with KPK as:", "options": {"A": "Bajaur Division", "B": "Bajaur District", "C": "Bajaur Tehsil", "D": "Bajaur Zone"}, "correct_answer": "B", "topic": "Geography", "difficulty": "medium"},
    {"id": "KPPSC-PK-00195", "text": "BRT (Bus Rapid Transit) in Peshawar started in:", "options": {"A": "2018", "B": "2020", "C": "2022", "D": "2024"}, "correct_answer": "B", "topic": "Development", "difficulty": "easy"},
    {"id": "KPPSC-PK-00196", "text": "Billion Tree Tsunami project was launched by:", "options": {"A": "Federal Government", "B": "KPK Government", "C": "Punjab Government", "D": "Sindh Government"}, "correct_answer": "B", "topic": "Environment", "difficulty": "easy"},
    {"id": "KPPSC-PK-00197", "text": "KPK Assembly has total seats:", "options": {"A": "115", "B": "124", "C": "130", "D": "140"}, "correct_answer": "B", "topic": "Constitutional History", "difficulty": "hard"},
    {"id": "KPPSC-PK-00198", "text": "Chief Minister of KPK is elected by:", "options": {"A": "Governor", "B": "Provincial Assembly", "C": "President", "D": "Prime Minister"}, "correct_answer": "B", "topic": "Constitutional History", "difficulty": "easy"},
    {"id": "KPPSC-PK-00199", "text": "Governor of KPK is appointed by:", "options": {"A": "Chief Minister", "B": "President", "C": "Prime Minister", "D": "Provincial Assembly"}, "correct_answer": "B", "topic": "Constitutional History", "difficulty": "easy"},
    {"id": "KPPSC-PK-00200", "text": "The current number of union councils in KPK is approximately:", "options": {"A": "2500", "B": "3500", "C": "4500", "D": "5500"}, "correct_answer": "B", "topic": "Administration", "difficulty": "hard"}
  ]
}
