{
  "$schema": "exam-tutor/question-bank/v1",
  "metadata": {"exam_type": "SPSC", "subject": "Computer Science", "topic": "Basic IT", "source": "compiled", "created_at": "2026-01-26T00:00:00Z", "question_count": 50},
  "questions": [
    {"id": "SPSC-CS-00001", "text": "Which generation of computers used vacuum tubes?", "options": {"A": "First", "B": "Second", "C": "Third", "D": "Fourth"}, "correct_answer": "A", "topic": "History", "difficulty": "easy"},
    {"id": "SPSC-CS-00002", "text": "Which generation of computers used transistors?", "options": {"A": "First", "B": "Second", "C": "Third", "D": "Fourth"}, "correct_answer": "B", "topic": "History", "difficulty": "easy"},
    {"id": "SPSC-CS-00003", "text": "Which generation of computers used integrated circuits?", "options": {"A": "First", "B": "Second", "C": "Third", "D": "Fourth"}, "correct_answer": "C", "topic": "History", "difficulty": "easy"},
    {"id": "SPSC-CS-00004", "text": "Which generation of computers used microprocessors?", "options": {"A": "First", "B": "Second", "C": "Third", "D": "Fourth"}, "correct_answer": "D", "topic": "History", "difficulty": "easy"},
    {"id": "SPSC-CS-00005", "text": "BIOS stands for:", "options": {"A": "Basic Input Output System", "B": "Binary Input Output System", "C": "Basic Internal Operating System", "D": "Binary Internal Output System"}, "correct_answer": "A", "topic": "Hardware", "difficulty": "easy"},
    {"id": "SPSC-CS-00006", "text": "ALU stands for:", "options": {"A": "Arithmetic Logic Unit", "B": "Array Logic Unit", "C": "Arithmetic Linear Unit", "D": "Application Logic Unit"}, "correct_answer": "A", "topic": "Hardware", "difficulty": "easy"},
    {"id": "SPSC-CS-00007", "text": "Which is primary memory?", "options": {"A": "Hard disk", "B": "RAM", "C": "CD-ROM", "D": "USB drive"}, "correct_answer": "B", "topic": "Memory", "difficulty": "easy"},
    {"id": "SPSC-CS-00008", "text": "Which is secondary memory?", "options": {"A": "RAM", "B": "ROM", "C": "Hard disk", "D": "Cache"}, "correct_answer": "C", "topic": "Memory", "difficulty": "easy"},
    {"id": "SPSC-CS-00009", "text": "Cache memory is:", "options": {"A": "Slower than RAM", "B": "Faster than RAM", "C": "Same as RAM", "D": "Same as ROM"}, "correct_answer": "B", "topic": "Memory", "difficulty": "medium"},
    {"id": "SPSC-CS-00010", "text": "SSD stands for:", "options": {"A": "Solid State Drive", "B": "System State Drive", "C": "Solid System Disk", "D": "Static Storage Device"}, "correct_answer": "A", "topic": "Hardware", "difficulty": "easy"},
    {"id": "SPSC-CS-00011", "text": "HDD stands for:", "options": {"A": "High Density Disk", "B": "Hard Disk Drive", "C": "High Data Drive", "D": "Hardware Data Disk"}, "correct_answer": "B", "topic": "Hardware", "difficulty": "easy"},
    {"id": "SPSC-CS-00012", "text": "Which is faster?", "options": {"A": "HDD", "B": "SSD", "C": "CD-ROM", "D": "Floppy disk"}, "correct_answer": "B", "topic": "Hardware", "difficulty": "easy"},
    {"id": "SPSC-CS-00013", "text": "GPU stands for:", "options": {"A": "Graphics Processing Unit", "B": "General Processing Unit", "C": "Graphics Program Unit", "D": "General Program Unit"}, "correct_answer": "A", "topic": "Hardware", "difficulty": "easy"},
    {"id": "SPSC-CS-00014", "text": "The resolution of monitor is measured in:", "options": {"A": "Bytes", "B": "Pixels", "C": "Hertz", "D": "Inches"}, "correct_answer": "B", "topic": "Hardware", "difficulty": "easy"},
    {"id": "SPSC-CS-00015", "text": "Which port is used to connect keyboard?", "options": {"A": "HDMI", "B": "VGA", "C": "USB", "D": "Ethernet"}, "correct_answer": "C", "topic": "Hardware", "difficulty": "easy"},
    {"id": "SPSC-CS-00016", "text": "Which is not an input device?", "options": {"A": "Scanner", "B": "Webcam", "C": "Projector", "D": "Microphone"}, "correct_answer": "C", "topic": "Hardware", "difficulty": "easy"},
    {"id": "SPSC-CS-00017", "text": "OCR stands for:", "options": {"A": "Optical Character Recognition", "B": "Optical Code Reader", "C": "Output Character Recognition", "D": "Online Character Reader"}, "correct_answer": "A", "topic": "Hardware", "difficulty": "medium"},
    {"id": "SPSC-CS-00018", "text": "Which device is both input and output?", "options": {"A": "Printer", "B": "Monitor", "C": "Touch screen", "D": "Speaker"}, "correct_answer": "C", "topic": "Hardware", "difficulty": "medium"},
    {"id": "SPSC-CS-00019", "text": "SQL stands for:", "options": {"A": "Structured Query Language", "B": "Simple Query Language", "C": "Standard Query Language", "D": "System Query Language"}, "correct_answer": "A", "topic": "Database", "difficulty": "easy"},
    {"id": "SPSC-CS-00020", "text": "DBMS stands for:", "options": {"A": "Database Management System", "B": "Data Base Manager Software", "C": "Digital Base Management System", "D": "Data Binary Management System"}, "correct_answer": "A", "topic": "Database", "difficulty": "easy"},
    {"id": "SPSC-CS-00021", "text": "Which is a database software?", "options": {"A": "Excel", "B": "MySQL", "C": "Word", "D": "Chrome"}, "correct_answer": "B", "topic": "Database", "difficulty": "easy"},
    {"id": "SPSC-CS-00022", "text": "A row in a database table is called:", "options": {"A": "Field", "B": "Record", "C": "Column", "D": "Attribute"}, "correct_answer": "B", "topic": "Database", "difficulty": "easy"},
    {"id": "SPSC-CS-00023", "text": "A column in a database table is called:", "options": {"A": "Field", "B": "Record", "C": "Row", "D": "Tuple"}, "correct_answer": "A", "topic": "Database", "difficulty": "easy"},
    {"id": "SPSC-CS-00024", "text": "Primary key is:", "options": {"A": "Always duplicate", "B": "Always unique", "C": "Optional", "D": "Null"}, "correct_answer": "B", "topic": "Database", "difficulty": "easy"},
    {"id": "SPSC-CS-00025", "text": "Which is a cloud storage service?", "options": {"A": "Google Drive", "B": "MS Word", "C": "Photoshop", "D": "VLC"}, "correct_answer": "A", "topic": "Cloud", "difficulty": "easy"},
    {"id": "SPSC-CS-00026", "text": "Which is not a cloud service provider?", "options": {"A": "AWS", "B": "Azure", "C": "Adobe", "D": "Google Cloud"}, "correct_answer": "C", "topic": "Cloud", "difficulty": "medium"},
    {"id": "SPSC-CS-00027", "text": "SaaS stands for:", "options": {"A": "Software as a Service", "B": "System as a Service", "C": "Storage as a Service", "D": "Security as a Service"}, "correct_answer": "A", "topic": "Cloud", "difficulty": "medium"},
    {"id": "SPSC-CS-00028", "text": "ISP stands for:", "options": {"A": "Internet Service Provider", "B": "Internal Service Protocol", "C": "Internet System Provider", "D": "Internal System Protocol"}, "correct_answer": "A", "topic": "Networking", "difficulty": "easy"},
    {"id": "SPSC-CS-00029", "text": "FTP stands for:", "options": {"A": "File Transfer Protocol", "B": "File Transit Protocol", "C": "Fast Transfer Protocol", "D": "File Text Protocol"}, "correct_answer": "A", "topic": "Networking", "difficulty": "easy"},
    {"id": "SPSC-CS-00030", "text": "SMTP is used for:", "options": {"A": "Web browsing", "B": "File transfer", "C": "Sending emails", "D": "Video streaming"}, "correct_answer": "C", "topic": "Networking", "difficulty": "medium"},
    {"id": "SPSC-CS-00031", "text": "Which protocol is used for secure web browsing?", "options": {"A": "HTTP", "B": "HTTPS", "C": "FTP", "D": "SMTP"}, "correct_answer": "B", "topic": "Networking", "difficulty": "easy"},
    {"id": "SPSC-CS-00032", "text": "Firewall is used for:", "options": {"A": "Printing", "B": "Security", "C": "Storage", "D": "Display"}, "correct_answer": "B", "topic": "Security", "difficulty": "easy"},
    {"id": "SPSC-CS-00033", "text": "Antivirus software protects against:", "options": {"A": "Power surge", "B": "Malware", "C": "Hardware failure", "D": "Network congestion"}, "correct_answer": "B", "topic": "Security", "difficulty": "easy"},
    {"id": "SPSC-CS-00034", "text": "Phishing is:", "options": {"A": "A type of fish", "B": "A cyberattack", "C": "A software", "D": "A hardware"}, "correct_answer": "B", "topic": "Security", "difficulty": "easy"},
    {"id": "SPSC-CS-00035", "text": "Strong password should have:", "options": {"A": "Only letters", "B": "Only numbers", "C": "Mix of letters, numbers, symbols", "D": "Only symbols"}, "correct_answer": "C", "topic": "Security", "difficulty": "easy"},
    {"id": "SPSC-CS-00036", "text": "In Excel, SUM function is used to:", "options": {"A": "Count cells", "B": "Add numbers", "C": "Find average", "D": "Find maximum"}, "correct_answer": "B", "topic": "MS Office", "difficulty": "easy"},
    {"id": "SPSC-CS-00037", "text": "In Excel, AVERAGE function calculates:", "options": {"A": "Total", "B": "Mean", "C": "Maximum", "D": "Minimum"}, "correct_answer": "B", "topic": "MS Office", "difficulty": "easy"},
    {"id": "SPSC-CS-00038", "text": "In Excel, COUNT function:", "options": {"A": "Adds numbers", "B": "Counts cells with numbers", "C": "Finds average", "D": "Finds maximum"}, "correct_answer": "B", "topic": "MS Office", "difficulty": "easy"},
    {"id": "SPSC-CS-00039", "text": "Cell address B5 means:", "options": {"A": "Row B, Column 5", "B": "Column B, Row 5", "C": "Cell number 5", "D": "Block B5"}, "correct_answer": "B", "topic": "MS Office", "difficulty": "easy"},
    {"id": "SPSC-CS-00040", "text": "In PowerPoint, slide transition is:", "options": {"A": "Adding text", "B": "Animation between slides", "C": "Printing slides", "D": "Deleting slides"}, "correct_answer": "B", "topic": "MS Office", "difficulty": "easy"},
    {"id": "SPSC-CS-00041", "text": "Which view shows all slides at once in PowerPoint?", "options": {"A": "Normal view", "B": "Slide sorter view", "C": "Reading view", "D": "Outline view"}, "correct_answer": "B", "topic": "MS Office", "difficulty": "medium"},
    {"id": "SPSC-CS-00042", "text": "Mail merge is used to:", "options": {"A": "Send emails", "B": "Create personalized documents", "C": "Merge files", "D": "Delete emails"}, "correct_answer": "B", "topic": "MS Office", "difficulty": "medium"},
    {"id": "SPSC-CS-00043", "text": "What is the default file extension for MS Word 2007 and later?", "options": {"A": ".doc", "B": ".docx", "C": ".txt", "D": ".rtf"}, "correct_answer": "B", "topic": "MS Office", "difficulty": "easy"},
    {"id": "SPSC-CS-00044", "text": "Which key is used to start slideshow from beginning?", "options": {"A": "F1", "B": "F5", "C": "F7", "D": "F12"}, "correct_answer": "B", "topic": "MS Office", "difficulty": "medium"},
    {"id": "SPSC-CS-00045", "text": "ASCII stands for:", "options": {"A": "American Standard Code for Information Interchange", "B": "Advanced Standard Code for Information Interchange", "C": "American System Code for Information Integration", "D": "Advanced System Code for Information Integration"}, "correct_answer": "A", "topic": "Data Representation", "difficulty": "medium"},
    {"id": "SPSC-CS-00046", "text": "How many bits are in a byte?", "options": {"A": "4", "B": "8", "C": "16", "D": "32"}, "correct_answer": "B", "topic": "Data Representation", "difficulty": "easy"},
    {"id": "SPSC-CS-00047", "text": "Binary equivalent of decimal 10 is:", "options": {"A": "1000", "B": "1010", "C": "1100", "D": "1110"}, "correct_answer": "B", "topic": "Number Systems", "difficulty": "medium"},
    {"id": "SPSC-CS-00048", "text": "Decimal equivalent of binary 1100 is:", "options": {"A": "10", "B": "11", "C": "12", "D": "13"}, "correct_answer": "C", "topic": "Number Systems", "difficulty": "medium"},
    {"id": "SPSC-CS-00049", "text": "What does GUI stand for?", "options": {"A": "Graphical User Interface", "B": "General User Interface", "C": "Graphical Unified Interface", "D": "General Unified Interface"}, "correct_answer": "A", "topic": "Software", "difficulty": "easy"},
    {"id": "SPSC-CS-00050", "text": "Which is an example of system software?", "options": {"A": "MS Word", "B": "Windows", "C": "Chrome", "D": "Photoshop"}, "correct_answer": "B", "topic": "Software", "difficulty": "easy"}
  ]
}
